{
  "exp_dir": "../artifacts/baseline_fixed_participants_e20_earlystop",
  "data_base_dir": "../datasets/Для участников",
  "train_csv": "../datasets/Для участников/train.csv",
  "train_ratio": 0.98,
  "min_val_utts": 11,
  "seed": 2026,
  "sample_rate": 16000,
  "train_chunk_seconds": 3.0,
  "val_chunk_seconds": 6.0,
  "n_mels": 80,
  "n_fft": 400,
  "hop_length": 160,
  "batch_size": 256,
  "num_workers": 8,
  "epochs": 20,
  "lr": 0.001,
  "weight_decay": 0.00001,
  "embed_dim": 192,
  "val_ks": [10],
  "device": "auto",
  "checkpoint_metric": "precision@10",
  "early_stopping_enabled": true,
  "early_stopping_metric": "precision@10",
  "early_stopping_mode": "max",
  "early_stopping_min_delta": 0.0005,
  "early_stopping_patience": 3,
  "early_stopping_min_epochs": 6,
  "early_stopping_restore_best": true,
  "scheduler": "reduce_on_plateau",
  "scheduler_factor": 0.5,
  "scheduler_patience": 1,
  "scheduler_threshold": 0.0005,
  "scheduler_min_lr": 0.00001,
  "grad_clip_norm": 5.0
}
